postalcodes_mexico/__init__.py
postalcodes_mexico/cli.py
postalcodes_mexico/postalcodes_mexico.py
postalcodes_mexico/utils.py
postalcodes_mexico/data/postalcodes.sqlite3
postalcodes_mexico-0.4.2.dist-info/DESCRIPTION.rst
postalcodes_mexico-0.4.2.dist-info/METADATA
postalcodes_mexico-0.4.2.dist-info/RECORD
postalcodes_mexico-0.4.2.dist-info/WHEEL
postalcodes_mexico-0.4.2.dist-info/entry_points.txt
postalcodes_mexico-0.4.2.dist-info/metadata.json
postalcodes_mexico-0.4.2.dist-info/top_level.txt
