Metadata-Version: 2.0
Name: postalcodes-mexico
Version: 0.4.2
Summary: Determines large parts of a Mexican postal address from its postal code (C.P.).
Home-page: https://github.com/flowfx/postalcodes_mexico
Author: Florian Posdziech
Author-email: hallo@flowfx.de
License: MIT license
Keywords: postalcodes_mexico
Platform: UNKNOWN
Classifier: Development Status :: 2 - Pre-Alpha
Classifier: Intended Audience :: Developers
Classifier: License :: OSI Approved :: MIT License
Classifier: Natural Language :: English
Classifier: Programming Language :: Python :: 3
Classifier: Programming Language :: Python :: 3.5
Classifier: Programming Language :: Python :: 3.6
Requires-Dist: Click (>=6.0)
Requires-Dist: xmltodict
